abagnale/__init__.py
abagnale/__version__.py
abagnale-0.0.1.dist-info/METADATA
abagnale-0.0.1.dist-info/RECORD
abagnale-0.0.1.dist-info/WHEEL
abagnale-0.0.1.dist-info/top_level.txt
